README.md
setup.py
oagre/__init__.py
oagre/oagre.py
oagre.egg-info/PKG-INFO
oagre.egg-info/SOURCES.txt
oagre.egg-info/dependency_links.txt
oagre.egg-info/requires.txt
oagre.egg-info/top_level.txt