Metadata-Version: 2.1
Name: oagre
Version: 0.1.0
Summary: Python library for building gradient boosted meta-learner regression.
Home-page: http://john-hawkins.github.io
Author: John Hawkins
Author-email: john@getting-data-science-done.com
License: MIT
Project-URL: Documentation, https://oagre.readthedocs.io
Project-URL: Source, https://github.com/john-hawkins/oagre
Project-URL: Tracker, https://github.com/john-hawkins/oagre/issues
Classifier: Intended Audience :: Developers
Classifier: Intended Audience :: Science/Research
Classifier: Programming Language :: Python :: 3
Classifier: Programming Language :: Python :: 3.6
Classifier: Programming Language :: Python :: 3.7
Classifier: Programming Language :: Python :: 3.8
Classifier: License :: OSI Approved :: MIT License
Classifier: Topic :: Scientific/Engineering
Classifier: Topic :: Scientific/Engineering :: Artificial Intelligence
